lib/Decorators.py
lib/Functions.py
lib/Terminal.py
lib/__init__.py
pyIPCMI/__init__.py
pyIPCMI/Base/Exceptions.py
pyIPCMI/Base/Executable.py
pyIPCMI/Base/Logging.py
pyIPCMI/Base/Project.py
pyIPCMI/Base/Shared.py
pyIPCMI/Base/__init__.py
pyIPCMI/Compiler/ISECompiler.py
pyIPCMI/Compiler/LSECompiler.py
pyIPCMI/Compiler/QuartusCompiler.py
pyIPCMI/Compiler/VivadoCompiler.py
pyIPCMI/Compiler/XCICompiler.py
pyIPCMI/Compiler/XCOCompiler.py
pyIPCMI/Compiler/XSTCompiler.py
pyIPCMI/Compiler/__init__.py
pyIPCMI/DataBase/Config.py
pyIPCMI/DataBase/Entity.py
pyIPCMI/DataBase/Solution.py
pyIPCMI/DataBase/TestCase.py
pyIPCMI/DataBase/__init__.py
pyIPCMI/Parser/__init__.py
pyIPCMI/Processor/__init__.py
pyIPCMI/Simulator/ActiveHDLSimulator.py
pyIPCMI/Simulator/CocotbSimulator.py
pyIPCMI/Simulator/GHDLSimulator.py
pyIPCMI/Simulator/ISESimulator.py
pyIPCMI/Simulator/ModelSimSimulator.py
pyIPCMI/Simulator/QuestaSimulator.py
pyIPCMI/Simulator/RivieraPROSimulator.py
pyIPCMI/Simulator/VivadoSimulator.py
pyIPCMI/Simulator/__init__.py
pyIPCMI/ToolChain/GHDL.py
pyIPCMI/ToolChain/GNU.py
pyIPCMI/ToolChain/GTKWave.py
pyIPCMI/ToolChain/Git.py
pyIPCMI/ToolChain/PoC.py
pyIPCMI/ToolChain/Windows.py
pyIPCMI/ToolChain/__init__.py
pyIPCMI/ToolChain/Aldec/ActiveHDL.py
pyIPCMI/ToolChain/Aldec/RivieraPRO.py
pyIPCMI/ToolChain/Aldec/__init__.py
pyIPCMI/ToolChain/Altera/ModelSim.py
pyIPCMI/ToolChain/Altera/Quartus.py
pyIPCMI/ToolChain/Altera/__init__.py
pyIPCMI/ToolChain/Intel/ModelSim.py
pyIPCMI/ToolChain/Intel/Quartus.py
pyIPCMI/ToolChain/Intel/__init__.py
pyIPCMI/ToolChain/Lattice/ActiveHDL.py
pyIPCMI/ToolChain/Lattice/Diamond.py
pyIPCMI/ToolChain/Lattice/Synplify.py
pyIPCMI/ToolChain/Lattice/__init__.py
pyIPCMI/ToolChain/Mentor/ModelSim.py
pyIPCMI/ToolChain/Mentor/QuestaSim.py
pyIPCMI/ToolChain/Mentor/__init__.py
pyIPCMI/ToolChain/Synopsys/__init__.py
pyIPCMI/ToolChain/Xilinx/ISE.py
pyIPCMI/ToolChain/Xilinx/Vivado.py
pyIPCMI/ToolChain/Xilinx/__init__.py
pyIPCMI-1.1.5.dist-info/LICENSE.md
pyIPCMI-1.1.5.dist-info/METADATA
pyIPCMI-1.1.5.dist-info/WHEEL
pyIPCMI-1.1.5.dist-info/top_level.txt
pyIPCMI-1.1.5.dist-info/RECORD
