Metadata-Version: 2.1
Name: pyIPCMI
Version: 1.1.5
Summary: An IP Core Management Infrastructure written in Python - pyIPCMI.
Home-page: https://github.com/Paebbels/pyIPCMI
Author: Patrick Lehmann
Author-email: Paebbels@gmail.com
License: UNKNOWN
Project-URL: Documentation, https://pyIPCMI.readthedocs.io/en/latest/
Project-URL: Source Code, https://github.com/Paebbels/pyIPCMI
Project-URL: Issue Tracker, https://github.com/Paebbels/pyIPCMI/issues
Keywords: Python3 Generic-Library IP-Core,Management,Packaging,Simulation,Synthesis,Pre-Processing,Post-Processing
Platform: UNKNOWN
Classifier: License :: OSI Approved :: Apache Software License
Classifier: Operating System :: OS Independent
Classifier: Operating System :: Microsoft :: Windows :: Windows 7
Classifier: Operating System :: Microsoft :: Windows :: Windows 8
Classifier: Operating System :: Microsoft :: Windows :: Windows 10
Classifier: Operating System :: POSIX :: Linux
Classifier: Operating System :: MacOS
Classifier: Programming Language :: Python :: 3 :: Only
Classifier: Programming Language :: Python :: 3.5
Classifier: Programming Language :: Python :: 3.6
Classifier: Programming Language :: Python :: 3.7
Classifier: Programming Language :: Python :: 3.8
Classifier: Development Status :: 4 - Beta
Classifier: Intended Audience :: Developers
Classifier: Topic :: Scientific/Engineering :: Electronic Design Automation (EDA)
Classifier: Topic :: Software Development :: Build Tools
Classifier: Topic :: Software Development :: Testing
Classifier: Topic :: Software Development :: Testing :: Unit
Classifier: Topic :: Software Development :: Version Control :: Git
Classifier: Topic :: System :: Archiving :: Packaging
Classifier: Topic :: Text Processing :: Filters
Classifier: Topic :: Utilities
Requires-Python: >=3.5
Requires-Dist: colorama (>=0.4.1)
Requires-Dist: py-flags (>=1.1.3)
Requires-Dist: pyExceptions
Requires-Dist: pyAttributes
Requires-Dist: pyCallBy
Requires-Dist: pyExtendedConfigParser
Requires-Dist: pyTokenizer
Requires-Dist: pyExploringCodeDOMParser
Requires-Dist: SphinxExtensions
Requires-Dist: pyIPCMI.Parser.Files
Requires-Dist: pyIPCMI.Parser.Rules
